asytest/__init__.py
asytest/__main__.py
asytest/_version.py
asytest/asytest.py
asytest-0.1.5.dist-info/LICENSE
asytest-0.1.5.dist-info/METADATA
asytest-0.1.5.dist-info/WHEEL
asytest-0.1.5.dist-info/top_level.txt
asytest-0.1.5.dist-info/RECORD
