Metadata-Version: 2.1
Name: asytest
Version: 0.1.5
Summary: Tiny async test framework for python 
Author: Pavel Rabetski
Project-URL: Homepage, https://github.com/pavradev/asytest
Project-URL: Bug Tracker, https://github.com/pavradev/asytest/issues
Classifier: Programming Language :: Python :: 3
Classifier: License :: OSI Approved :: MIT License
Classifier: Operating System :: OS Independent
Requires-Python: >=3.10
License-File: LICENSE
Requires-Dist: asyncio (==3.4.3)
Provides-Extra: dev
Requires-Dist: pytest ; extra == 'dev'
Requires-Dist: pip-tools ; extra == 'dev'
